[{"month": "2015-01", "kpi_commits_month": null, "kpi_commits_month_log": null, "kpi_new_issues_month": 18.0, "kpi_new_issues_month_log": null, "kpi_new_prs_month": 40.0, "kpi_new_prs_month_log": null, "kpi_active_contributors_month": 47.0, "kpi_stars_delta_month": 18.0, "lat_issue_response_median": 15.5, "lat_pr_resolution_median": 1.0, "bus_factor": 19.0, "kpi_release_count_month": null, "kpi_release_count_month_log": null, "kpi_code_change_lines_month": 152262.0, "kpi_code_change_lines_month_log": null, "kpi_activity": 126.16, "kpi_openrank": 17.45, "kpi_attention": 68.0}, {"month": "2015-02", "kpi_commits_month": null, "kpi_commits_month_log": null, "kpi_new_issues_month": 17.0, "kpi_new_issues_month_log": null, "kpi_new_prs_month": 57.0, "kpi_new_prs_month_log": null, "kpi_active_contributors_month": 52.0, "kpi_stars_delta_month": 17.0, "lat_issue_response_median": 17.0, "lat_pr_resolution_median": 1.0, "bus_factor": 20.0, "kpi_release_count_month": null, "kpi_release_count_month_log": null, "kpi_code_change_lines_month": 130024.0, "kpi_code_change_lines_month_log": null, "kpi_activity": 166.79, "kpi_openrank": 24.77, "kpi_attention": 73.0}, {"month": "2015-03", "kpi_commits_month": null, "kpi_commits_month_log": null, "kpi_new_issues_month": 33.0, "kpi_new_issues_month_log": null, "kpi_new_prs_month": 77.0, "kpi_new_prs_month_log": null, "kpi_active_contributors_month": 58.0, "kpi_stars_delta_month": 28.0, "lat_issue_response_median": 9.0, "lat_pr_resolution_median": 1.0, "bus_factor": 12.0, "kpi_release_count_month": null, "kpi_release_count_month_log": null, "kpi_code_change_lines_month": 455750.0, "kpi_code_change_lines_month_log": null, "kpi_activity": 214.41, "kpi_openrank": 38.7, "kpi_attention": 102.0}, {"month": "2015-04", "kpi_commits_month": null, "kpi_commits_month_log": null, "kpi_new_issues_month": 26.0, "kpi_new_issues_month_log": null, "kpi_new_prs_month": 20.0, "kpi_new_prs_month_log": null, "kpi_active_contributors_month": 47.0, "kpi_stars_delta_month": 24.0, "lat_issue_response_median": 40.0, "lat_pr_resolution_median": 1.0, "bus_factor": 41.0, "kpi_release_count_month": null, "kpi_release_count_month_log": null, "kpi_code_change_lines_month": 158170.0, "kpi_code_change_lines_month_log": null, "kpi_activity": 87.61, "kpi_openrank": 25.61, "kpi_attention": 66.0}, {"month": "2015-05", "kpi_commits_month": null, "kpi_commits_month_log": null, "kpi_new_issues_month": 40.0, "kpi_new_issues_month_log": null, "kpi_new_prs_month": 51.0, "kpi_new_prs_month_log": null, "kpi_active_contributors_month": 78.0, "kpi_stars_delta_month": 26.0, "lat_issue_response_median": 31.5, "lat_pr_resolution_median": 1.0, "bus_factor": 35.0, "kpi_release_count_month": null, "kpi_release_count_month_log": null, "kpi_code_change_lines_month": 318927.0, "kpi_code_change_lines_month_log": null, "kpi_activity": 186.68, "kpi_openrank": 41.37, "kpi_attention": 92.0}, {"month": "2015-06", "kpi_commits_month": null, "kpi_commits_month_log": null, "kpi_new_issues_month": 37.0, "kpi_new_issues_month_log": null, "kpi_new_prs_month": 73.0, "kpi_new_prs_month_log": null, "kpi_active_contributors_month": 102.0, "kpi_stars_delta_month": 29.0, "lat_issue_response_median": 1.0, "lat_pr_resolution_median": 1.0, "bus_factor": 27.0, "kpi_release_count_month": null, "kpi_release_count_month_log": null, "kpi_code_change_lines_month": 243522.0, "kpi_code_change_lines_month_log": null, "kpi_activity": 259.55, "kpi_openrank": 55.47, "kpi_attention": 93.0}, {"month": "2015-07", "kpi_commits_month": null, "kpi_commits_month_log": null, "kpi_new_issues_month": 48.0, "kpi_new_issues_month_log": null, "kpi_new_prs_month": 74.0, "kpi_new_prs_month_log": null, "kpi_active_contributors_month": 100.0, "kpi_stars_delta_month": 28.0, "lat_issue_response_median": 7.0, "lat_pr_resolution_median": 1.0, "bus_factor": 26.0, "kpi_release_count_month": null, "kpi_release_count_month_log": null, "kpi_code_change_lines_month": 531056.0, "kpi_code_change_lines_month_log": null, "kpi_activity": 269.73, "kpi_openrank": 58.51, "kpi_attention": 92.0}, {"month": "2015-08", "kpi_commits_month": null, "kpi_commits_month_log": null, "kpi_new_issues_month": 61.0, "kpi_new_issues_month_log": null, "kpi_new_prs_month": 92.0, "kpi_new_prs_month_log": null, "kpi_active_contributors_month": 92.0, "kpi_stars_delta_month": 35.0, "lat_issue_response_median": 15.0, "lat_pr_resolution_median": 1.0, "bus_factor": 29.0, "kpi_release_count_month": null, "kpi_release_count_month_log": null, "kpi_code_change_lines_month": 683413.0, "kpi_code_change_lines_month_log": null, "kpi_activity": 264.88, "kpi_openrank": 66.38, "kpi_attention": 97.0}, {"month": "2015-09", "kpi_commits_month": null, "kpi_commits_month_log": null, "kpi_new_issues_month": 33.0, "kpi_new_issues_month_log": null, "kpi_new_prs_month": 166.0, "kpi_new_prs_month_log": null, "kpi_active_contributors_month": 83.0, "kpi_stars_delta_month": 31.0, "lat_issue_response_median": 15.0, "lat_pr_resolution_median": 1.0, "bus_factor": 31.0, "kpi_release_count_month": null, "kpi_release_count_month_log": null, "kpi_code_change_lines_month": 487022.0, "kpi_code_change_lines_month_log": null, "kpi_activity": 273.73, "kpi_openrank": 81.68, "kpi_attention": 85.0}, {"month": "2015-10", "kpi_commits_month": null, "kpi_commits_month_log": null, "kpi_new_issues_month": 58.0, "kpi_new_issues_month_log": null, "kpi_new_prs_month": 139.0, "kpi_new_prs_month_log": null, "kpi_active_contributors_month": 110.0, "kpi_stars_delta_month": 36.0, "lat_issue_response_median": 22.0, "lat_pr_resolution_median": 0.0, "bus_factor": 26.0, "kpi_release_count_month": null, "kpi_release_count_month_log": null, "kpi_code_change_lines_month": 269318.0, "kpi_code_change_lines_month_log": null, "kpi_activity": 317.3, "kpi_openrank": 87.87, "kpi_attention": 106.0}, {"month": "2015-11", "kpi_commits_month": null, "kpi_commits_month_log": null, "kpi_new_issues_month": 69.0, "kpi_new_issues_month_log": null, "kpi_new_prs_month": 84.0, "kpi_new_prs_month_log": null, "kpi_active_contributors_month": 115.0, "kpi_stars_delta_month": 44.0, "lat_issue_response_median": 11.0, "lat_pr_resolution_median": 1.0, "bus_factor": 48.0, "kpi_release_count_month": null, "kpi_release_count_month_log": null, "kpi_code_change_lines_month": 230831.0, "kpi_code_change_lines_month_log": null, "kpi_activity": 274.55, "kpi_openrank": 91.38, "kpi_attention": 88.0}, {"month": "2015-12", "kpi_commits_month": null, "kpi_commits_month_log": null, "kpi_new_issues_month": 70.0, "kpi_new_issues_month_log": null, "kpi_new_prs_month": 120.0, "kpi_new_prs_month_log": null, "kpi_active_contributors_month": 117.0, "kpi_stars_delta_month": 23.0, "lat_issue_response_median": 13.0, "lat_pr_resolution_median": 1.0, "bus_factor": 33.0, "kpi_release_count_month": null, "kpi_release_count_month_log": null, "kpi_code_change_lines_month": 236580.0, "kpi_code_change_lines_month_log": null, "kpi_activity": 324.9, "kpi_openrank": 103.71, "kpi_attention": 73.0}, {"month": "2016-01", "kpi_commits_month": null, "kpi_commits_month_log": null, "kpi_new_issues_month": 40.0, "kpi_new_issues_month_log": null, "kpi_new_prs_month": 148.0, "kpi_new_prs_month_log": null, "kpi_active_contributors_month": 128.0, "kpi_stars_delta_month": 24.0, "lat_issue_response_median": 2.0, "lat_pr_resolution_median": 0.0, "bus_factor": 34.0, "kpi_release_count_month": null, "kpi_release_count_month_log": null, "kpi_code_change_lines_month": 343104.0, "kpi_code_change_lines_month_log": null, "kpi_activity": 328.37, "kpi_openrank": 112.17, "kpi_attention": 98.0}, {"month": "2016-02", "kpi_commits_month": null, "kpi_commits_month_log": null, "kpi_new_issues_month": 58.0, "kpi_new_issues_month_log": null, "kpi_new_prs_month": 84.0, "kpi_new_prs_month_log": null, "kpi_active_contributors_month": 130.0, "kpi_stars_delta_month": 32.0, "lat_issue_response_median": 1.0, "lat_pr_resolution_median": 1.0, "bus_factor": 51.0, "kpi_release_count_month": null, "kpi_release_count_month_log": null, "kpi_code_change_lines_month": 387738.0, "kpi_code_change_lines_month_log": null, "kpi_activity": 318.71, "kpi_openrank": 106.2, "kpi_attention": 84.0}, {"month": "2016-03", "kpi_commits_month": null, "kpi_commits_month_log": null, "kpi_new_issues_month": 65.0, "kpi_new_issues_month_log": null, "kpi_new_prs_month": 84.0, "kpi_new_prs_month_log": null, "kpi_active_contributors_month": 136.0, "kpi_stars_delta_month": 25.0, "lat_issue_response_median": 1.0, "lat_pr_resolution_median": 1.0, "bus_factor": 48.0, "kpi_release_count_month": null, "kpi_release_count_month_log": null, "kpi_code_change_lines_month": 509137.0, "kpi_code_change_lines_month_log": null, "kpi_activity": 308.92, "kpi_openrank": 103.05, "kpi_attention": 97.0}, {"month": "2016-04", "kpi_commits_month": null, "kpi_commits_month_log": null, "kpi_new_issues_month": 62.0, "kpi_new_issues_month_log": null, "kpi_new_prs_month": 88.0, "kpi_new_prs_month_log": null, "kpi_active_contributors_month": 114.0, "kpi_stars_delta_month": 26.0, "lat_issue_response_median": 3.0, "lat_pr_resolution_median": 1.0, "bus_factor": 48.0, "kpi_release_count_month": null, "kpi_release_count_month_log": null, "kpi_code_change_lines_month": 245658.0, "kpi_code_change_lines_month_log": null, "kpi_activity": 302.24, "kpi_openrank": 99.76, "kpi_attention": 96.0}, {"month": "2016-05", "kpi_commits_month": null, "kpi_commits_month_log": null, "kpi_new_issues_month": 100.0, "kpi_new_issues_month_log": null, "kpi_new_prs_month": 87.0, "kpi_new_prs_month_log": null, "kpi_active_contributors_month": 124.0, "kpi_stars_delta_month": 25.0, "lat_issue_response_median": 4.5, "lat_pr_resolution_median": 1.0, "bus_factor": 29.0, "kpi_release_count_month": null, "kpi_release_count_month_log": null, "kpi_code_change_lines_month": 296133.0, "kpi_code_change_lines_month_log": null, "kpi_activity": 360.11, "kpi_openrank": 108.58, "kpi_attention": 101.0}, {"month": "2016-06", "kpi_commits_month": null, "kpi_commits_month_log": null, "kpi_new_issues_month": 76.0, "kpi_new_issues_month_log": null, "kpi_new_prs_month": 97.0, "kpi_new_prs_month_log": null, "kpi_active_contributors_month": 135.0, "kpi_stars_delta_month": 32.0, "lat_issue_response_median": 2.0, "lat_pr_resolution_median": 2.0, "bus_factor": 34.0, "kpi_release_count_month": null, "kpi_release_count_month_log": null, "kpi_code_change_lines_month": 531241.0, "kpi_code_change_lines_month_log": null, "kpi_activity": 367.39, "kpi_openrank": 114.89, "kpi_attention": 112.0}, {"month": "2016-07", "kpi_commits_month": null, "kpi_commits_month_log": null, "kpi_new_issues_month": 57.0, "kpi_new_issues_month_log": null, "kpi_new_prs_month": 97.0, "kpi_new_prs_month_log": null, "kpi_active_contributors_month": 107.0, "kpi_stars_delta_month": 20.0, "lat_issue_response_median": 6.0, "lat_pr_resolution_median": 1.0, "bus_factor": 27.0, "kpi_release_count_month": null, "kpi_release_count_month_log": null, "kpi_code_change_lines_month": 479995.0, "kpi_code_change_lines_month_log": null, "kpi_activity": 302.97, "kpi_openrank": 113.84, "kpi_attention": 78.0}, {"month": "2016-08", "kpi_commits_month": null, "kpi_commits_month_log": null, "kpi_new_issues_month": 80.0, "kpi_new_issues_month_log": null, "kpi_new_prs_month": 93.0, "kpi_new_prs_month_log": null, "kpi_active_contributors_month": 128.0, "kpi_stars_delta_month": 32.0, "lat_issue_response_median": 4.0, "lat_pr_resolution_median": 2.0, "bus_factor": 31.0, "kpi_release_count_month": null, "kpi_release_count_month_log": null, "kpi_code_change_lines_month": 69653.0, "kpi_code_change_lines_month_log": null, "kpi_activity": 339.4, "kpi_openrank": 108.89, "kpi_attention": 78.0}, {"month": "2016-09", "kpi_commits_month": null, "kpi_commits_month_log": null, "kpi_new_issues_month": 71.0, "kpi_new_issues_month_log": null, "kpi_new_prs_month": 98.0, "kpi_new_prs_month_log": null, "kpi_active_contributors_month": 116.0, "kpi_stars_delta_month": 20.0, "lat_issue_response_median": 7.0, "lat_pr_resolution_median": 1.0, "bus_factor": 32.0, "kpi_release_count_month": null, "kpi_release_count_month_log": null, "kpi_code_change_lines_month": 155492.0, "kpi_code_change_lines_month_log": null, "kpi_activity": 339.33, "kpi_openrank": 115.2, "kpi_attention": 82.0}, {"month": "2016-10", "kpi_commits_month": null, "kpi_commits_month_log": null, "kpi_new_issues_month": 60.0, "kpi_new_issues_month_log": null, "kpi_new_prs_month": 59.0, "kpi_new_prs_month_log": null, "kpi_active_contributors_month": 104.0, "kpi_stars_delta_month": 24.0, "lat_issue_response_median": 1.0, "lat_pr_resolution_median": 4.0, "bus_factor": 27.0, "kpi_release_count_month": null, "kpi_release_count_month_log": null, "kpi_code_change_lines_month": 212964.0, "kpi_code_change_lines_month_log": null, "kpi_activity": 294.84, "kpi_openrank": 107.82, "kpi_attention": 78.0}, {"month": "2016-11", "kpi_commits_month": null, "kpi_commits_month_log": null, "kpi_new_issues_month": 27.0, "kpi_new_issues_month_log": null, "kpi_new_prs_month": 46.0, "kpi_new_prs_month_log": null, "kpi_active_contributors_month": 101.0, "kpi_stars_delta_month": 24.0, "lat_issue_response_median": 1.0, "lat_pr_resolution_median": 6.0, "bus_factor": 36.0, "kpi_release_count_month": null, "kpi_release_count_month_log": null, "kpi_code_change_lines_month": 368478.0, "kpi_code_change_lines_month_log": null, "kpi_activity": 254.3, "kpi_openrank": 98.45, "kpi_attention": 64.0}, {"month": "2016-12", "kpi_commits_month": null, "kpi_commits_month_log": null, "kpi_new_issues_month": 46.0, "kpi_new_issues_month_log": null, "kpi_new_prs_month": 54.0, "kpi_new_prs_month_log": null, "kpi_active_contributors_month": 96.0, "kpi_stars_delta_month": 18.0, "lat_issue_response_median": 40.5, "lat_pr_resolution_median": 1.0, "bus_factor": 21.0, "kpi_release_count_month": null, "kpi_release_count_month_log": null, "kpi_code_change_lines_month": 405180.0, "kpi_code_change_lines_month_log": null, "kpi_activity": 270.93, "kpi_openrank": 116.04, "kpi_attention": 60.0}, {"month": "2017-01", "kpi_commits_month": null, "kpi_commits_month_log": null, "kpi_new_issues_month": 51.0, "kpi_new_issues_month_log": null, "kpi_new_prs_month": 54.0, "kpi_new_prs_month_log": null, "kpi_active_contributors_month": 116.0, "kpi_stars_delta_month": 20.0, "lat_issue_response_median": 4.0, "lat_pr_resolution_median": 3.0, "bus_factor": 34.0, "kpi_release_count_month": null, "kpi_release_count_month_log": null, "kpi_code_change_lines_month": 86950.0, "kpi_code_change_lines_month_log": null, "kpi_activity": 262.92, "kpi_openrank": 103.99, "kpi_attention": 80.0}, {"month": "2017-02", "kpi_commits_month": null, "kpi_commits_month_log": null, "kpi_new_issues_month": 37.0, "kpi_new_issues_month_log": null, "kpi_new_prs_month": 65.0, "kpi_new_prs_month_log": null, "kpi_active_contributors_month": 111.0, "kpi_stars_delta_month": 29.0, "lat_issue_response_median": 7.0, "lat_pr_resolution_median": 3.0, "bus_factor": 22.0, "kpi_release_count_month": null, "kpi_release_count_month_log": null, "kpi_code_change_lines_month": 90523.0, "kpi_code_change_lines_month_log": null, "kpi_activity": 321.66, "kpi_openrank": 105.88, "kpi_attention": 109.0}, {"month": "2017-03", "kpi_commits_month": null, "kpi_commits_month_log": null, "kpi_new_issues_month": 74.0, "kpi_new_issues_month_log": null, "kpi_new_prs_month": 81.0, "kpi_new_prs_month_log": null, "kpi_active_contributors_month": 130.0, "kpi_stars_delta_month": 38.0, "lat_issue_response_median": 5.0, "lat_pr_resolution_median": 2.0, "bus_factor": 44.0, "kpi_release_count_month": null, "kpi_release_count_month_log": null, "kpi_code_change_lines_month": 216003.0, "kpi_code_change_lines_month_log": null, "kpi_activity": 352.04, "kpi_openrank": 106.71, "kpi_attention": 146.0}, {"month": "2017-04", "kpi_commits_month": null, "kpi_commits_month_log": null, "kpi_new_issues_month": 76.0, "kpi_new_issues_month_log": null, "kpi_new_prs_month": 92.0, "kpi_new_prs_month_log": null, "kpi_active_contributors_month": 128.0, "kpi_stars_delta_month": 27.0, "lat_issue_response_median": 6.0, "lat_pr_resolution_median": 2.5, "bus_factor": 31.0, "kpi_release_count_month": null, "kpi_release_count_month_log": null, "kpi_code_change_lines_month": 523913.0, "kpi_code_change_lines_month_log": null, "kpi_activity": 362.35, "kpi_openrank": 121.55, "kpi_attention": 79.0}, {"month": "2017-05", "kpi_commits_month": null, "kpi_commits_month_log": null, "kpi_new_issues_month": 79.0, "kpi_new_issues_month_log": null, "kpi_new_prs_month": 115.0, "kpi_new_prs_month_log": null, "kpi_active_contributors_month": 164.0, "kpi_stars_delta_month": 27.0, "lat_issue_response_median": 2.0, "lat_pr_resolution_median": 1.0, "bus_factor": 42.0, "kpi_release_count_month": null, "kpi_release_count_month_log": null, "kpi_code_change_lines_month": 66771.0, "kpi_code_change_lines_month_log": null, "kpi_activity": 458.8, "kpi_openrank": 130.18, "kpi_attention": 127.0}, {"month": "2017-06", "kpi_commits_month": null, "kpi_commits_month_log": null, "kpi_new_issues_month": 67.0, "kpi_new_issues_month_log": null, "kpi_new_prs_month": 96.0, "kpi_new_prs_month_log": null, "kpi_active_contributors_month": 176.0, "kpi_stars_delta_month": 28.0, "lat_issue_response_median": 3.0, "lat_pr_resolution_median": 3.0, "bus_factor": 35.0, "kpi_release_count_month": null, "kpi_release_count_month_log": null, "kpi_code_change_lines_month": 978628.0, "kpi_code_change_lines_month_log": null, "kpi_activity": 524.22, "kpi_openrank": 158.18, "kpi_attention": 106.0}, {"month": "2017-07", "kpi_commits_month": null, "kpi_commits_month_log": null, "kpi_new_issues_month": 68.0, "kpi_new_issues_month_log": null, "kpi_new_prs_month": 96.0, "kpi_new_prs_month_log": null, "kpi_active_contributors_month": 147.0, "kpi_stars_delta_month": 27.0, "lat_issue_response_median": 2.0, "lat_pr_resolution_median": 4.0, "bus_factor": 55.0, "kpi_release_count_month": null, "kpi_release_count_month_log": null, "kpi_code_change_lines_month": 535058.0, "kpi_code_change_lines_month_log": null, "kpi_activity": 382.28, "kpi_openrank": 153.3, "kpi_attention": 125.0}, {"month": "2017-08", "kpi_commits_month": null, "kpi_commits_month_log": null, "kpi_new_issues_month": 75.0, "kpi_new_issues_month_log": null, "kpi_new_prs_month": 70.0, "kpi_new_prs_month_log": null, "kpi_active_contributors_month": 153.0, "kpi_stars_delta_month": 27.0, "lat_issue_response_median": 20.5, "lat_pr_resolution_median": 2.0, "bus_factor": 48.0, "kpi_release_count_month": null, "kpi_release_count_month_log": null, "kpi_code_change_lines_month": 303836.0, "kpi_code_change_lines_month_log": null, "kpi_activity": 378.39, "kpi_openrank": 151.53, "kpi_attention": 103.0}, {"month": "2017-09", "kpi_commits_month": null, "kpi_commits_month_log": null, "kpi_new_issues_month": 92.0, "kpi_new_issues_month_log": null, "kpi_new_prs_month": 66.0, "kpi_new_prs_month_log": null, "kpi_active_contributors_month": 138.0, "kpi_stars_delta_month": 21.0, "lat_issue_response_median": 27.0, "lat_pr_resolution_median": 2.0, "bus_factor": 97.0, "kpi_release_count_month": null, "kpi_release_count_month_log": null, "kpi_code_change_lines_month": 525167.0, "kpi_code_change_lines_month_log": null, "kpi_activity": 296.05, "kpi_openrank": 137.09, "kpi_attention": 111.0}, {"month": "2017-10", "kpi_commits_month": null, "kpi_commits_month_log": null, "kpi_new_issues_month": 92.0, "kpi_new_issues_month_log": null, "kpi_new_prs_month": 111.0, "kpi_new_prs_month_log": null, "kpi_active_contributors_month": 172.0, "kpi_stars_delta_month": 31.0, "lat_issue_response_median": 2.0, "lat_pr_resolution_median": 3.0, "bus_factor": 37.0, "kpi_release_count_month": null, "kpi_release_count_month_log": null, "kpi_code_change_lines_month": 951297.0, "kpi_code_change_lines_month_log": null, "kpi_activity": 508.55, "kpi_openrank": 161.27, "kpi_attention": 133.0}, {"month": "2017-11", "kpi_commits_month": null, "kpi_commits_month_log": null, "kpi_new_issues_month": 75.0, "kpi_new_issues_month_log": null, "kpi_new_prs_month": 87.0, "kpi_new_prs_month_log": null, "kpi_active_contributors_month": 157.0, "kpi_stars_delta_month": 24.0, "lat_issue_response_median": 1.0, "lat_pr_resolution_median": 4.0, "bus_factor": 36.0, "kpi_release_count_month": null, "kpi_release_count_month_log": null, "kpi_code_change_lines_month": 364889.0, "kpi_code_change_lines_month_log": null, "kpi_activity": 451.44, "kpi_openrank": 170.87, "kpi_attention": 104.0}, {"month": "2017-12", "kpi_commits_month": null, "kpi_commits_month_log": null, "kpi_new_issues_month": 65.0, "kpi_new_issues_month_log": null, "kpi_new_prs_month": 81.0, "kpi_new_prs_month_log": null, "kpi_active_contributors_month": 128.0, "kpi_stars_delta_month": 19.0, "lat_issue_response_median": 11.0, "lat_pr_resolution_median": 3.0, "bus_factor": 34.0, "kpi_release_count_month": null, "kpi_release_count_month_log": null, "kpi_code_change_lines_month": 332566.0, "kpi_code_change_lines_month_log": null, "kpi_activity": 395.07, "kpi_openrank": 170.67, "kpi_attention": 75.0}, {"month": "2018-01", "kpi_commits_month": null, "kpi_commits_month_log": null, "kpi_new_issues_month": 99.0, "kpi_new_issues_month_log": null, "kpi_new_prs_month": 108.0, "kpi_new_prs_month_log": null, "kpi_active_contributors_month": 161.0, "kpi_stars_delta_month": 29.0, "lat_issue_response_median": 7.0, "lat_pr_resolution_median": 2.5, "bus_factor": 23.0, "kpi_release_count_month": null, "kpi_release_count_month_log": null, "kpi_code_change_lines_month": -171093.0, "kpi_code_change_lines_month_log": null, "kpi_activity": 498.73, "kpi_openrank": 181.14, "kpi_attention": 111.0}, {"month": "2018-02", "kpi_commits_month": null, "kpi_commits_month_log": null, "kpi_new_issues_month": 96.0, "kpi_new_issues_month_log": null, "kpi_new_prs_month": 132.0, "kpi_new_prs_month_log": null, "kpi_active_contributors_month": 158.0, "kpi_stars_delta_month": 29.0, "lat_issue_response_median": 2.0, "lat_pr_resolution_median": 1.0, "bus_factor": 37.0, "kpi_release_count_month": null, "kpi_release_count_month_log": null, "kpi_code_change_lines_month": 171367.0, "kpi_code_change_lines_month_log": null, "kpi_activity": 475.52, "kpi_openrank": 181.34, "kpi_attention": 97.0}, {"month": "2018-03", "kpi_commits_month": null, "kpi_commits_month_log": null, "kpi_new_issues_month": 91.0, "kpi_new_issues_month_log": null, "kpi_new_prs_month": 106.0, "kpi_new_prs_month_log": null, "kpi_active_contributors_month": 191.0, "kpi_stars_delta_month": 30.0, "lat_issue_response_median": 1.0, "lat_pr_resolution_median": 3.0, "bus_factor": 37.0, "kpi_release_count_month": null, "kpi_release_count_month_log": null, "kpi_code_change_lines_month": 352653.0, "kpi_code_change_lines_month_log": null, "kpi_activity": 549.61, "kpi_openrank": 188.96, "kpi_attention": 120.0}, {"month": "2018-04", "kpi_commits_month": null, "kpi_commits_month_log": null, "kpi_new_issues_month": 77.0, "kpi_new_issues_month_log": null, "kpi_new_prs_month": 134.0, "kpi_new_prs_month_log": null, "kpi_active_contributors_month": 181.0, "kpi_stars_delta_month": 42.0, "lat_issue_response_median": 4.0, "lat_pr_resolution_median": 2.0, "bus_factor": 40.0, "kpi_release_count_month": null, "kpi_release_count_month_log": null, "kpi_code_change_lines_month": 39578.0, "kpi_code_change_lines_month_log": null, "kpi_activity": 523.07, "kpi_openrank": 198.74, "kpi_attention": 128.0}, {"month": "2018-05", "kpi_commits_month": null, "kpi_commits_month_log": null, "kpi_new_issues_month": 100.0, "kpi_new_issues_month_log": null, "kpi_new_prs_month": 145.0, "kpi_new_prs_month_log": null, "kpi_active_contributors_month": 210.0, "kpi_stars_delta_month": 27.0, "lat_issue_response_median": 5.0, "lat_pr_resolution_median": 1.0, "bus_factor": 41.0, "kpi_release_count_month": null, "kpi_release_count_month_log": null, "kpi_code_change_lines_month": 361227.0, "kpi_code_change_lines_month_log": null, "kpi_activity": 627.9, "kpi_openrank": 223.67, "kpi_attention": 133.0}, {"month": "2018-06", "kpi_commits_month": null, "kpi_commits_month_log": null, "kpi_new_issues_month": 90.0, "kpi_new_issues_month_log": null, "kpi_new_prs_month": 113.0, "kpi_new_prs_month_log": null, "kpi_active_contributors_month": 195.0, "kpi_stars_delta_month": 27.0, "lat_issue_response_median": 3.0, "lat_pr_resolution_median": 2.0, "bus_factor": 42.0, "kpi_release_count_month": null, "kpi_release_count_month_log": null, "kpi_code_change_lines_month": 605223.0, "kpi_code_change_lines_month_log": null, "kpi_activity": 548.76, "kpi_openrank": 219.95, "kpi_attention": 111.0}, {"month": "2018-07", "kpi_commits_month": null, "kpi_commits_month_log": null, "kpi_new_issues_month": 106.0, "kpi_new_issues_month_log": null, "kpi_new_prs_month": 130.0, "kpi_new_prs_month_log": null, "kpi_active_contributors_month": 211.0, "kpi_stars_delta_month": 37.0, "lat_issue_response_median": 2.0, "lat_pr_resolution_median": 1.0, "bus_factor": 38.0, "kpi_release_count_month": null, "kpi_release_count_month_log": null, "kpi_code_change_lines_month": 774870.0, "kpi_code_change_lines_month_log": null, "kpi_activity": 542.1, "kpi_openrank": 228.14, "kpi_attention": 125.0}, {"month": "2018-08", "kpi_commits_month": null, "kpi_commits_month_log": null, "kpi_new_issues_month": 115.0, "kpi_new_issues_month_log": null, "kpi_new_prs_month": 153.0, "kpi_new_prs_month_log": null, "kpi_active_contributors_month": 186.0, "kpi_stars_delta_month": 38.0, "lat_issue_response_median": 13.0, "lat_pr_resolution_median": 3.0, "bus_factor": 34.0, "kpi_release_count_month": null, "kpi_release_count_month_log": null, "kpi_code_change_lines_month": 225327.0, "kpi_code_change_lines_month_log": null, "kpi_activity": 541.38, "kpi_openrank": 219.68, "kpi_attention": 138.0}, {"month": "2018-09", "kpi_commits_month": null, "kpi_commits_month_log": null, "kpi_new_issues_month": 105.0, "kpi_new_issues_month_log": null, "kpi_new_prs_month": 181.0, "kpi_new_prs_month_log": null, "kpi_active_contributors_month": 206.0, "kpi_stars_delta_month": 24.0, "lat_issue_response_median": 2.5, "lat_pr_resolution_median": 1.0, "bus_factor": 33.0, "kpi_release_count_month": null, "kpi_release_count_month_log": null, "kpi_code_change_lines_month": 739452.0, "kpi_code_change_lines_month_log": null, "kpi_activity": 713.25, "kpi_openrank": 241.32, "kpi_attention": 124.0}, {"month": "2018-10", "kpi_commits_month": null, "kpi_commits_month_log": null, "kpi_new_issues_month": 117.0, "kpi_new_issues_month_log": null, "kpi_new_prs_month": 134.0, "kpi_new_prs_month_log": null, "kpi_active_contributors_month": 235.0, "kpi_stars_delta_month": 62.0, "lat_issue_response_median": 1.0, "lat_pr_resolution_median": 3.0, "bus_factor": 72.0, "kpi_release_count_month": null, "kpi_release_count_month_log": null, "kpi_code_change_lines_month": 338713.0, "kpi_code_change_lines_month_log": null, "kpi_activity": 561.66, "kpi_openrank": 229.11, "kpi_attention": 182.0}, {"month": "2018-11", "kpi_commits_month": null, "kpi_commits_month_log": null, "kpi_new_issues_month": 90.0, "kpi_new_issues_month_log": null, "kpi_new_prs_month": 133.0, "kpi_new_prs_month_log": null, "kpi_active_contributors_month": 205.0, "kpi_stars_delta_month": 32.0, "lat_issue_response_median": 3.0, "lat_pr_resolution_median": 3.0, "bus_factor": 65.0, "kpi_release_count_month": null, "kpi_release_count_month_log": null, "kpi_code_change_lines_month": 780371.0, "kpi_code_change_lines_month_log": null, "kpi_activity": 482.12, "kpi_openrank": 227.56, "kpi_attention": 124.0}, {"month": "2018-12", "kpi_commits_month": null, "kpi_commits_month_log": null, "kpi_new_issues_month": 63.0, "kpi_new_issues_month_log": null, "kpi_new_prs_month": 156.0, "kpi_new_prs_month_log": null, "kpi_active_contributors_month": 151.0, "kpi_stars_delta_month": 33.0, "lat_issue_response_median": 4.0, "lat_pr_resolution_median": 1.0, "bus_factor": 53.0, "kpi_release_count_month": null, "kpi_release_count_month_log": null, "kpi_code_change_lines_month": -68167.0, "kpi_code_change_lines_month_log": null, "kpi_activity": 407.81, "kpi_openrank": 223.96, "kpi_attention": 111.0}, {"month": "2019-01", "kpi_commits_month": null, "kpi_commits_month_log": null, "kpi_new_issues_month": 69.0, "kpi_new_issues_month_log": null, "kpi_new_prs_month": 159.0, "kpi_new_prs_month_log": null, "kpi_active_contributors_month": 183.0, "kpi_stars_delta_month": 41.0, "lat_issue_response_median": 1.0, "lat_pr_resolution_median": 1.0, "bus_factor": 58.0, "kpi_release_count_month": null, "kpi_release_count_month_log": null, "kpi_code_change_lines_month": 738983.0, "kpi_code_change_lines_month_log": null, "kpi_activity": 472.81, "kpi_openrank": 221.8, "kpi_attention": 163.0}, {"month": "2019-02", "kpi_commits_month": null, "kpi_commits_month_log": null, "kpi_new_issues_month": 84.0, "kpi_new_issues_month_log": null, "kpi_new_prs_month": 111.0, "kpi_new_prs_month_log": null, "kpi_active_contributors_month": 212.0, "kpi_stars_delta_month": 44.0, "lat_issue_response_median": 0.5, "lat_pr_resolution_median": 2.0, "bus_factor": 40.0, "kpi_release_count_month": null, "kpi_release_count_month_log": null, "kpi_code_change_lines_month": 364822.0, "kpi_code_change_lines_month_log": null, "kpi_activity": 571.09, "kpi_openrank": 226.3, "kpi_attention": 154.0}, {"month": "2019-03", "kpi_commits_month": null, "kpi_commits_month_log": null, "kpi_new_issues_month": 111.0, "kpi_new_issues_month_log": null, "kpi_new_prs_month": 139.0, "kpi_new_prs_month_log": null, "kpi_active_contributors_month": 230.0, "kpi_stars_delta_month": 48.0, "lat_issue_response_median": 1.0, "lat_pr_resolution_median": 2.0, "bus_factor": 75.0, "kpi_release_count_month": null, "kpi_release_count_month_log": null, "kpi_code_change_lines_month": 968599.0, "kpi_code_change_lines_month_log": null, "kpi_activity": 610.79, "kpi_openrank": 230.39, "kpi_attention": 162.0}, {"month": "2019-04", "kpi_commits_month": null, "kpi_commits_month_log": null, "kpi_new_issues_month": 95.0, "kpi_new_issues_month_log": null, "kpi_new_prs_month": 120.0, "kpi_new_prs_month_log": null, "kpi_active_contributors_month": 226.0, "kpi_stars_delta_month": 63.0, "lat_issue_response_median": 1.0, "lat_pr_resolution_median": 1.0, "bus_factor": 47.0, "kpi_release_count_month": null, "kpi_release_count_month_log": null, "kpi_code_change_lines_month": 750797.0, "kpi_code_change_lines_month_log": null, "kpi_activity": 605.83, "kpi_openrank": 229.93, "kpi_attention": 155.0}, {"month": "2019-05", "kpi_commits_month": null, "kpi_commits_month_log": null, "kpi_new_issues_month": 108.0, "kpi_new_issues_month_log": null, "kpi_new_prs_month": 123.0, "kpi_new_prs_month_log": null, "kpi_active_contributors_month": 230.0, "kpi_stars_delta_month": 40.0, "lat_issue_response_median": 2.0, "lat_pr_resolution_median": 3.0, "bus_factor": 50.0, "kpi_release_count_month": null, "kpi_release_count_month_log": null, "kpi_code_change_lines_month": 628213.0, "kpi_code_change_lines_month_log": null, "kpi_activity": 605.81, "kpi_openrank": 231.31, "kpi_attention": 188.0}, {"month": "2019-06", "kpi_commits_month": null, "kpi_commits_month_log": null, "kpi_new_issues_month": 85.0, "kpi_new_issues_month_log": null, "kpi_new_prs_month": 101.0, "kpi_new_prs_month_log": null, "kpi_active_contributors_month": 226.0, "kpi_stars_delta_month": 41.0, "lat_issue_response_median": 1.0, "lat_pr_resolution_median": 2.0, "bus_factor": 76.0, "kpi_release_count_month": null, "kpi_release_count_month_log": null, "kpi_code_change_lines_month": 336037.0, "kpi_code_change_lines_month_log": null, "kpi_activity": 548.99, "kpi_openrank": 207.29, "kpi_attention": 135.0}, {"month": "2019-07", "kpi_commits_month": null, "kpi_commits_month_log": null, "kpi_new_issues_month": 90.0, "kpi_new_issues_month_log": null, "kpi_new_prs_month": 138.0, "kpi_new_prs_month_log": null, "kpi_active_contributors_month": 245.0, "kpi_stars_delta_month": 42.0, "lat_issue_response_median": 1.0, "lat_pr_resolution_median": 1.0, "bus_factor": 90.0, "kpi_release_count_month": null, "kpi_release_count_month_log": null, "kpi_code_change_lines_month": 675203.0, "kpi_code_change_lines_month_log": null, "kpi_activity": 625.02, "kpi_openrank": 216.61, "kpi_attention": 174.0}, {"month": "2019-08", "kpi_commits_month": null, "kpi_commits_month_log": null, "kpi_new_issues_month": 87.0, "kpi_new_issues_month_log": null, "kpi_new_prs_month": 97.0, "kpi_new_prs_month_log": null, "kpi_active_contributors_month": 203.0, "kpi_stars_delta_month": 55.0, "lat_issue_response_median": 2.0, "lat_pr_resolution_median": 3.0, "bus_factor": 60.0, "kpi_release_count_month": null, "kpi_release_count_month_log": null, "kpi_code_change_lines_month": 133033.0, "kpi_code_change_lines_month_log": null, "kpi_activity": 486.23, "kpi_openrank": 200.83, "kpi_attention": 179.0}, {"month": "2019-09", "kpi_commits_month": null, "kpi_commits_month_log": null, "kpi_new_issues_month": 88.0, "kpi_new_issues_month_log": null, "kpi_new_prs_month": 112.0, "kpi_new_prs_month_log": null, "kpi_active_contributors_month": 214.0, "kpi_stars_delta_month": 33.0, "lat_issue_response_median": 3.5, "lat_pr_resolution_median": 4.0, "bus_factor": 70.0, "kpi_release_count_month": null, "kpi_release_count_month_log": null, "kpi_code_change_lines_month": 873793.0, "kpi_code_change_lines_month_log": null, "kpi_activity": 571.42, "kpi_openrank": 211.69, "kpi_attention": 173.0}, {"month": "2019-10", "kpi_commits_month": null, "kpi_commits_month_log": null, "kpi_new_issues_month": 101.0, "kpi_new_issues_month_log": null, "kpi_new_prs_month": 185.0, "kpi_new_prs_month_log": null, "kpi_active_contributors_month": 231.0, "kpi_stars_delta_month": 39.0, "lat_issue_response_median": 5.0, "lat_pr_resolution_median": 2.0, "bus_factor": 46.0, "kpi_release_count_month": null, "kpi_release_count_month_log": null, "kpi_code_change_lines_month": 1459243.0, "kpi_code_change_lines_month_log": null, "kpi_activity": 702.62, "kpi_openrank": 208.0, "kpi_attention": 181.0}, {"month": "2019-11", "kpi_commits_month": null, "kpi_commits_month_log": null, "kpi_new_issues_month": 104.0, "kpi_new_issues_month_log": null, "kpi_new_prs_month": 84.0, "kpi_new_prs_month_log": null, "kpi_active_contributors_month": 197.0, "kpi_stars_delta_month": 33.0, "lat_issue_response_median": 14.0, "lat_pr_resolution_median": 2.0, "bus_factor": 57.0, "kpi_release_count_month": null, "kpi_release_count_month_log": null, "kpi_code_change_lines_month": 189667.0, "kpi_code_change_lines_month_log": null, "kpi_activity": 475.5, "kpi_openrank": 186.7, "kpi_attention": 101.0}, {"month": "2019-12", "kpi_commits_month": null, "kpi_commits_month_log": null, "kpi_new_issues_month": 65.0, "kpi_new_issues_month_log": null, "kpi_new_prs_month": 126.0, "kpi_new_prs_month_log": null, "kpi_active_contributors_month": 189.0, "kpi_stars_delta_month": 63.0, "lat_issue_response_median": 1.0, "lat_pr_resolution_median": 1.5, "bus_factor": 63.0, "kpi_release_count_month": null, "kpi_release_count_month_log": null, "kpi_code_change_lines_month": -215420.0, "kpi_code_change_lines_month_log": null, "kpi_activity": 456.91, "kpi_openrank": 168.76, "kpi_attention": 157.0}, {"month": "2020-01", "kpi_commits_month": null, "kpi_commits_month_log": null, "kpi_new_issues_month": 77.0, "kpi_new_issues_month_log": null, "kpi_new_prs_month": 115.0, "kpi_new_prs_month_log": null, "kpi_active_contributors_month": 237.0, "kpi_stars_delta_month": 90.0, "lat_issue_response_median": 1.0, "lat_pr_resolution_median": 3.0, "bus_factor": 75.0, "kpi_release_count_month": null, "kpi_release_count_month_log": null, "kpi_code_change_lines_month": 446174.0, "kpi_code_change_lines_month_log": null, "kpi_activity": 551.92, "kpi_openrank": 187.74, "kpi_attention": 206.0}, {"month": "2020-02", "kpi_commits_month": null, "kpi_commits_month_log": null, "kpi_new_issues_month": 86.0, "kpi_new_issues_month_log": null, "kpi_new_prs_month": 127.0, "kpi_new_prs_month_log": null, "kpi_active_contributors_month": 235.0, "kpi_stars_delta_month": 55.0, "lat_issue_response_median": 1.0, "lat_pr_resolution_median": 1.0, "bus_factor": 81.0, "kpi_release_count_month": null, "kpi_release_count_month_log": null, "kpi_code_change_lines_month": 1214003.0, "kpi_code_change_lines_month_log": null, "kpi_activity": 540.44, "kpi_openrank": 178.07, "kpi_attention": 157.0}, {"month": "2020-03", "kpi_commits_month": null, "kpi_commits_month_log": null, "kpi_new_issues_month": 111.0, "kpi_new_issues_month_log": null, "kpi_new_prs_month": 142.0, "kpi_new_prs_month_log": null, "kpi_active_contributors_month": 207.0, "kpi_stars_delta_month": 45.0, "lat_issue_response_median": 2.0, "lat_pr_resolution_median": 2.0, "bus_factor": 81.0, "kpi_release_count_month": null, "kpi_release_count_month_log": null, "kpi_code_change_lines_month": 933223.0, "kpi_code_change_lines_month_log": null, "kpi_activity": 523.27, "kpi_openrank": 162.21, "kpi_attention": 169.0}, {"month": "2020-04", "kpi_commits_month": null, "kpi_commits_month_log": null, "kpi_new_issues_month": 95.0, "kpi_new_issues_month_log": null, "kpi_new_prs_month": 216.0, "kpi_new_prs_month_log": null, "kpi_active_contributors_month": 260.0, "kpi_stars_delta_month": 59.0, "lat_issue_response_median": 1.0, "lat_pr_resolution_median": 1.0, "bus_factor": 84.0, "kpi_release_count_month": null, "kpi_release_count_month_log": null, "kpi_code_change_lines_month": 1427703.0, "kpi_code_change_lines_month_log": null, "kpi_activity": 639.44, "kpi_openrank": 178.98, "kpi_attention": 207.0}, {"month": "2020-05", "kpi_commits_month": null, "kpi_commits_month_log": null, "kpi_new_issues_month": 97.0, "kpi_new_issues_month_log": null, "kpi_new_prs_month": 164.0, "kpi_new_prs_month_log": null, "kpi_active_contributors_month": 228.0, "kpi_stars_delta_month": 105.0, "lat_issue_response_median": 2.0, "lat_pr_resolution_median": 1.0, "bus_factor": 75.0, "kpi_release_count_month": null, "kpi_release_count_month_log": null, "kpi_code_change_lines_month": 1383800.0, "kpi_code_change_lines_month_log": null, "kpi_activity": 559.01, "kpi_openrank": 177.52, "kpi_attention": 265.0}, {"month": "2020-06", "kpi_commits_month": null, "kpi_commits_month_log": null, "kpi_new_issues_month": 94.0, "kpi_new_issues_month_log": null, "kpi_new_prs_month": 176.0, "kpi_new_prs_month_log": null, "kpi_active_contributors_month": 274.0, "kpi_stars_delta_month": 59.0, "lat_issue_response_median": 1.0, "lat_pr_resolution_median": 1.0, "bus_factor": 103.0, "kpi_release_count_month": null, "kpi_release_count_month_log": null, "kpi_code_change_lines_month": 576592.0, "kpi_code_change_lines_month_log": null, "kpi_activity": 660.87, "kpi_openrank": 192.72, "kpi_attention": 233.0}, {"month": "2020-07", "kpi_commits_month": null, "kpi_commits_month_log": null, "kpi_new_issues_month": 86.0, "kpi_new_issues_month_log": null, "kpi_new_prs_month": 170.0, "kpi_new_prs_month_log": null, "kpi_active_contributors_month": 254.0, "kpi_stars_delta_month": 63.0, "lat_issue_response_median": 1.0, "lat_pr_resolution_median": 1.0, "bus_factor": 84.0, "kpi_release_count_month": null, "kpi_release_count_month_log": null, "kpi_code_change_lines_month": 439013.0, "kpi_code_change_lines_month_log": null, "kpi_activity": 601.11, "kpi_openrank": 187.48, "kpi_attention": 199.0}, {"month": "2020-08", "kpi_commits_month": null, "kpi_commits_month_log": null, "kpi_new_issues_month": 90.0, "kpi_new_issues_month_log": null, "kpi_new_prs_month": 166.0, "kpi_new_prs_month_log": null, "kpi_active_contributors_month": 231.0, "kpi_stars_delta_month": 38.0, "lat_issue_response_median": 1.0, "lat_pr_resolution_median": 1.0, "bus_factor": 80.0, "kpi_release_count_month": null, "kpi_release_count_month_log": null, "kpi_code_change_lines_month": 700190.0, "kpi_code_change_lines_month_log": null, "kpi_activity": 555.45, "kpi_openrank": 189.23, "kpi_attention": 138.0}, {"month": "2020-09", "kpi_commits_month": null, "kpi_commits_month_log": null, "kpi_new_issues_month": 104.0, "kpi_new_issues_month_log": null, "kpi_new_prs_month": 202.0, "kpi_new_prs_month_log": null, "kpi_active_contributors_month": 268.0, "kpi_stars_delta_month": 36.0, "lat_issue_response_median": 1.0, "lat_pr_resolution_median": 2.0, "bus_factor": 90.0, "kpi_release_count_month": null, "kpi_release_count_month_log": null, "kpi_code_change_lines_month": 686365.0, "kpi_code_change_lines_month_log": null, "kpi_activity": 655.65, "kpi_openrank": 213.86, "kpi_attention": 156.0}, {"month": "2020-10", "kpi_commits_month": null, "kpi_commits_month_log": null, "kpi_new_issues_month": 102.0, "kpi_new_issues_month_log": null, "kpi_new_prs_month": 157.0, "kpi_new_prs_month_log": null, "kpi_active_contributors_month": 303.0, "kpi_stars_delta_month": 78.0, "lat_issue_response_median": 1.0, "lat_pr_resolution_median": 2.0, "bus_factor": 95.0, "kpi_release_count_month": null, "kpi_release_count_month_log": null, "kpi_code_change_lines_month": 557947.0, "kpi_code_change_lines_month_log": null, "kpi_activity": 662.56, "kpi_openrank": 223.15, "kpi_attention": 194.0}, {"month": "2020-11", "kpi_commits_month": null, "kpi_commits_month_log": null, "kpi_new_issues_month": 67.0, "kpi_new_issues_month_log": null, "kpi_new_prs_month": 169.0, "kpi_new_prs_month_log": null, "kpi_active_contributors_month": 262.0, "kpi_stars_delta_month": 42.0, "lat_issue_response_median": 1.5, "lat_pr_resolution_median": 3.0, "bus_factor": 91.0, "kpi_release_count_month": null, "kpi_release_count_month_log": null, "kpi_code_change_lines_month": 856104.0, "kpi_code_change_lines_month_log": null, "kpi_activity": 645.27, "kpi_openrank": 231.52, "kpi_attention": 150.0}, {"month": "2020-12", "kpi_commits_month": null, "kpi_commits_month_log": null, "kpi_new_issues_month": 79.0, "kpi_new_issues_month_log": null, "kpi_new_prs_month": 168.0, "kpi_new_prs_month_log": null, "kpi_active_contributors_month": 193.0, "kpi_stars_delta_month": 35.0, "lat_issue_response_median": 2.0, "lat_pr_resolution_median": 1.0, "bus_factor": 85.0, "kpi_release_count_month": null, "kpi_release_count_month_log": null, "kpi_code_change_lines_month": 367266.0, "kpi_code_change_lines_month_log": null, "kpi_activity": 496.11, "kpi_openrank": 203.05, "kpi_attention": 155.0}, {"month": "2021-01", "kpi_commits_month": null, "kpi_commits_month_log": null, "kpi_new_issues_month": 54.0, "kpi_new_issues_month_log": null, "kpi_new_prs_month": 152.0, "kpi_new_prs_month_log": null, "kpi_active_contributors_month": 214.0, "kpi_stars_delta_month": 40.0, "lat_issue_response_median": 2.0, "lat_pr_resolution_median": 2.0, "bus_factor": 69.0, "kpi_release_count_month": null, "kpi_release_count_month_log": null, "kpi_code_change_lines_month": 488162.0, "kpi_code_change_lines_month_log": null, "kpi_activity": 516.56, "kpi_openrank": 197.99, "kpi_attention": 124.0}, {"month": "2021-02", "kpi_commits_month": null, "kpi_commits_month_log": null, "kpi_new_issues_month": 70.0, "kpi_new_issues_month_log": null, "kpi_new_prs_month": 216.0, "kpi_new_prs_month_log": null, "kpi_active_contributors_month": 233.0, "kpi_stars_delta_month": 121.0, "lat_issue_response_median": 4.0, "lat_pr_resolution_median": 1.0, "bus_factor": 72.0, "kpi_release_count_month": null, "kpi_release_count_month_log": null, "kpi_code_change_lines_month": 451532.0, "kpi_code_change_lines_month_log": null, "kpi_activity": 553.36, "kpi_openrank": 205.97, "kpi_attention": 253.0}, {"month": "2021-03", "kpi_commits_month": null, "kpi_commits_month_log": null, "kpi_new_issues_month": 98.0, "kpi_new_issues_month_log": null, "kpi_new_prs_month": 204.0, "kpi_new_prs_month_log": null, "kpi_active_contributors_month": 240.0, "kpi_stars_delta_month": 43.0, "lat_issue_response_median": 2.0, "lat_pr_resolution_median": 1.0, "bus_factor": 94.0, "kpi_release_count_month": null, "kpi_release_count_month_log": null, "kpi_code_change_lines_month": 723751.0, "kpi_code_change_lines_month_log": null, "kpi_activity": 631.94, "kpi_openrank": 211.36, "kpi_attention": 161.0}, {"month": "2021-04", "kpi_commits_month": null, "kpi_commits_month_log": null, "kpi_new_issues_month": 68.0, "kpi_new_issues_month_log": null, "kpi_new_prs_month": 137.0, "kpi_new_prs_month_log": null, "kpi_active_contributors_month": 194.0, "kpi_stars_delta_month": 52.0, "lat_issue_response_median": 3.0, "lat_pr_resolution_median": 2.0, "bus_factor": 69.0, "kpi_release_count_month": null, "kpi_release_count_month_log": null, "kpi_code_change_lines_month": 512753.0, "kpi_code_change_lines_month_log": null, "kpi_activity": 475.76, "kpi_openrank": 190.86, "kpi_attention": 152.0}, {"month": "2021-05", "kpi_commits_month": null, "kpi_commits_month_log": null, "kpi_new_issues_month": 68.0, "kpi_new_issues_month_log": null, "kpi_new_prs_month": 198.0, "kpi_new_prs_month_log": null, "kpi_active_contributors_month": 213.0, "kpi_stars_delta_month": 43.0, "lat_issue_response_median": 2.0, "lat_pr_resolution_median": 1.0, "bus_factor": 73.0, "kpi_release_count_month": null, "kpi_release_count_month_log": null, "kpi_code_change_lines_month": 654467.0, "kpi_code_change_lines_month_log": null, "kpi_activity": 530.29, "kpi_openrank": 207.81, "kpi_attention": 143.0}, {"month": "2021-06", "kpi_commits_month": null, "kpi_commits_month_log": null, "kpi_new_issues_month": 65.0, "kpi_new_issues_month_log": null, "kpi_new_prs_month": 156.0, "kpi_new_prs_month_log": null, "kpi_active_contributors_month": 178.0, "kpi_stars_delta_month": 37.0, "lat_issue_response_median": 3.0, "lat_pr_resolution_median": 1.0, "bus_factor": 41.0, "kpi_release_count_month": null, "kpi_release_count_month_log": null, "kpi_code_change_lines_month": -359323.0, "kpi_code_change_lines_month_log": null, "kpi_activity": 471.96, "kpi_openrank": 178.29, "kpi_attention": 147.0}, {"month": "2021-07", "kpi_commits_month": null, "kpi_commits_month_log": null, "kpi_new_issues_month": 60.0, "kpi_new_issues_month_log": null, "kpi_new_prs_month": 144.0, "kpi_new_prs_month_log": null, "kpi_active_contributors_month": 172.0, "kpi_stars_delta_month": 34.0, "lat_issue_response_median": 4.0, "lat_pr_resolution_median": 1.0, "bus_factor": 54.0, "kpi_release_count_month": null, "kpi_release_count_month_log": null, "kpi_code_change_lines_month": 222408.0, "kpi_code_change_lines_month_log": null, "kpi_activity": 393.79, "kpi_openrank": 171.66, "kpi_attention": 144.0}, {"month": "2021-08", "kpi_commits_month": null, "kpi_commits_month_log": null, "kpi_new_issues_month": 51.0, "kpi_new_issues_month_log": null, "kpi_new_prs_month": 125.0, "kpi_new_prs_month_log": null, "kpi_active_contributors_month": 165.0, "kpi_stars_delta_month": 42.0, "lat_issue_response_median": 2.5, "lat_pr_resolution_median": 1.0, "bus_factor": 54.0, "kpi_release_count_month": null, "kpi_release_count_month_log": null, "kpi_code_change_lines_month": 612529.0, "kpi_code_change_lines_month_log": null, "kpi_activity": 393.21, "kpi_openrank": 165.18, "kpi_attention": 152.0}, {"month": "2021-09", "kpi_commits_month": null, "kpi_commits_month_log": null, "kpi_new_issues_month": 73.0, "kpi_new_issues_month_log": null, "kpi_new_prs_month": 121.0, "kpi_new_prs_month_log": null, "kpi_active_contributors_month": 227.0, "kpi_stars_delta_month": 46.0, "lat_issue_response_median": 2.0, "lat_pr_resolution_median": 1.0, "bus_factor": 68.0, "kpi_release_count_month": null, "kpi_release_count_month_log": null, "kpi_code_change_lines_month": 281340.0, "kpi_code_change_lines_month_log": null, "kpi_activity": 463.4, "kpi_openrank": 167.1, "kpi_attention": 126.0}, {"month": "2021-10", "kpi_commits_month": null, "kpi_commits_month_log": null, "kpi_new_issues_month": 72.0, "kpi_new_issues_month_log": null, "kpi_new_prs_month": 136.0, "kpi_new_prs_month_log": null, "kpi_active_contributors_month": 216.0, "kpi_stars_delta_month": 49.0, "lat_issue_response_median": 52.0, "lat_pr_resolution_median": 14.5, "bus_factor": 64.0, "kpi_release_count_month": null, "kpi_release_count_month_log": null, "kpi_code_change_lines_month": 87874.0, "kpi_code_change_lines_month_log": null, "kpi_activity": 484.0, "kpi_openrank": 179.0, "kpi_attention": 153.0}, {"month": "2021-11", "kpi_commits_month": null, "kpi_commits_month_log": null, "kpi_new_issues_month": 82.0, "kpi_new_issues_month_log": null, "kpi_new_prs_month": 160.0, "kpi_new_prs_month_log": null, "kpi_active_contributors_month": 243.0, "kpi_stars_delta_month": 57.0, "lat_issue_response_median": 1.0, "lat_pr_resolution_median": 2.0, "bus_factor": 69.0, "kpi_release_count_month": null, "kpi_release_count_month_log": null, "kpi_code_change_lines_month": 1221258.0, "kpi_code_change_lines_month_log": null, "kpi_activity": 576.94, "kpi_openrank": 194.72, "kpi_attention": 185.0}, {"month": "2021-12", "kpi_commits_month": null, "kpi_commits_month_log": null, "kpi_new_issues_month": 65.0, "kpi_new_issues_month_log": null, "kpi_new_prs_month": 129.0, "kpi_new_prs_month_log": null, "kpi_active_contributors_month": 175.0, "kpi_stars_delta_month": 47.0, "lat_issue_response_median": 2.0, "lat_pr_resolution_median": 1.0, "bus_factor": 50.0, "kpi_release_count_month": null, "kpi_release_count_month_log": null, "kpi_code_change_lines_month": 201173.0, "kpi_code_change_lines_month_log": null, "kpi_activity": 403.99, "kpi_openrank": 183.48, "kpi_attention": 143.0}, {"month": "2022-01", "kpi_commits_month": null, "kpi_commits_month_log": null, "kpi_new_issues_month": 85.0, "kpi_new_issues_month_log": null, "kpi_new_prs_month": 159.0, "kpi_new_prs_month_log": null, "kpi_active_contributors_month": 203.0, "kpi_stars_delta_month": 39.0, "lat_issue_response_median": 3.0, "lat_pr_resolution_median": 2.0, "bus_factor": 57.0, "kpi_release_count_month": null, "kpi_release_count_month_log": null, "kpi_code_change_lines_month": 290562.0, "kpi_code_change_lines_month_log": null, "kpi_activity": 454.24, "kpi_openrank": 185.35, "kpi_attention": 143.0}, {"month": "2022-02", "kpi_commits_month": null, "kpi_commits_month_log": null, "kpi_new_issues_month": 62.0, "kpi_new_issues_month_log": null, "kpi_new_prs_month": 220.0, "kpi_new_prs_month_log": null, "kpi_active_contributors_month": 224.0, "kpi_stars_delta_month": 43.0, "lat_issue_response_median": 2.0, "lat_pr_resolution_median": 5.5, "bus_factor": 64.0, "kpi_release_count_month": null, "kpi_release_count_month_log": null, "kpi_code_change_lines_month": 944149.0, "kpi_code_change_lines_month_log": null, "kpi_activity": 514.04, "kpi_openrank": 190.61, "kpi_attention": 163.0}, {"month": "2022-03", "kpi_commits_month": null, "kpi_commits_month_log": null, "kpi_new_issues_month": 74.0, "kpi_new_issues_month_log": null, "kpi_new_prs_month": 306.0, "kpi_new_prs_month_log": null, "kpi_active_contributors_month": 224.0, "kpi_stars_delta_month": 45.0, "lat_issue_response_median": 1.0, "lat_pr_resolution_median": 2.0, "bus_factor": 46.0, "kpi_release_count_month": null, "kpi_release_count_month_log": null, "kpi_code_change_lines_month": 1036192.0, "kpi_code_change_lines_month_log": null, "kpi_activity": 636.21, "kpi_openrank": 205.25, "kpi_attention": 163.0}, {"month": "2022-04", "kpi_commits_month": null, "kpi_commits_month_log": null, "kpi_new_issues_month": 59.0, "kpi_new_issues_month_log": null, "kpi_new_prs_month": 225.0, "kpi_new_prs_month_log": null, "kpi_active_contributors_month": 202.0, "kpi_stars_delta_month": 67.0, "lat_issue_response_median": 2.0, "lat_pr_resolution_median": 1.0, "bus_factor": 55.0, "kpi_release_count_month": null, "kpi_release_count_month_log": null, "kpi_code_change_lines_month": 4072120.0, "kpi_code_change_lines_month_log": null, "kpi_activity": 459.73, "kpi_openrank": 199.95, "kpi_attention": 193.0}, {"month": "2022-05", "kpi_commits_month": null, "kpi_commits_month_log": null, "kpi_new_issues_month": 84.0, "kpi_new_issues_month_log": null, "kpi_new_prs_month": 218.0, "kpi_new_prs_month_log": null, "kpi_active_contributors_month": 185.0, "kpi_stars_delta_month": 39.0, "lat_issue_response_median": 2.0, "lat_pr_resolution_median": 1.0, "bus_factor": 61.0, "kpi_release_count_month": null, "kpi_release_count_month_log": null, "kpi_code_change_lines_month": 2204126.0, "kpi_code_change_lines_month_log": null, "kpi_activity": 487.09, "kpi_openrank": 195.65, "kpi_attention": 127.0}, {"month": "2022-06", "kpi_commits_month": null, "kpi_commits_month_log": null, "kpi_new_issues_month": 68.0, "kpi_new_issues_month_log": null, "kpi_new_prs_month": 357.0, "kpi_new_prs_month_log": null, "kpi_active_contributors_month": 193.0, "kpi_stars_delta_month": 61.0, "lat_issue_response_median": 2.0, "lat_pr_resolution_median": 2.0, "bus_factor": 66.0, "kpi_release_count_month": null, "kpi_release_count_month_log": null, "kpi_code_change_lines_month": 3921833.0, "kpi_code_change_lines_month_log": null, "kpi_activity": 516.07, "kpi_openrank": 204.54, "kpi_attention": 135.0}, {"month": "2022-07", "kpi_commits_month": null, "kpi_commits_month_log": null, "kpi_new_issues_month": 65.0, "kpi_new_issues_month_log": null, "kpi_new_prs_month": 163.0, "kpi_new_prs_month_log": null, "kpi_active_contributors_month": 162.0, "kpi_stars_delta_month": 43.0, "lat_issue_response_median": 2.5, "lat_pr_resolution_median": 1.0, "bus_factor": 38.0, "kpi_release_count_month": null, "kpi_release_count_month_log": null, "kpi_code_change_lines_month": 1605470.0, "kpi_code_change_lines_month_log": null, "kpi_activity": 465.12, "kpi_openrank": 207.66, "kpi_attention": 127.0}, {"month": "2022-08", "kpi_commits_month": null, "kpi_commits_month_log": null, "kpi_new_issues_month": 84.0, "kpi_new_issues_month_log": null, "kpi_new_prs_month": 170.0, "kpi_new_prs_month_log": null, "kpi_active_contributors_month": 201.0, "kpi_stars_delta_month": 43.0, "lat_issue_response_median": 2.0, "lat_pr_resolution_median": 1.0, "bus_factor": 65.0, "kpi_release_count_month": null, "kpi_release_count_month_log": null, "kpi_code_change_lines_month": 1014870.0, "kpi_code_change_lines_month_log": null, "kpi_activity": 495.76, "kpi_openrank": 199.74, "kpi_attention": 163.0}, {"month": "2022-09", "kpi_commits_month": null, "kpi_commits_month_log": null, "kpi_new_issues_month": 73.0, "kpi_new_issues_month_log": null, "kpi_new_prs_month": 266.0, "kpi_new_prs_month_log": null, "kpi_active_contributors_month": 195.0, "kpi_stars_delta_month": 47.0, "lat_issue_response_median": 1.5, "lat_pr_resolution_median": 1.0, "bus_factor": 82.0, "kpi_release_count_month": null, "kpi_release_count_month_log": null, "kpi_code_change_lines_month": 1623195.0, "kpi_code_change_lines_month_log": null, "kpi_activity": 520.75, "kpi_openrank": 201.24, "kpi_attention": 159.0}, {"month": "2022-10", "kpi_commits_month": null, "kpi_commits_month_log": null, "kpi_new_issues_month": 52.0, "kpi_new_issues_month_log": null, "kpi_new_prs_month": 198.0, "kpi_new_prs_month_log": null, "kpi_active_contributors_month": 179.0, "kpi_stars_delta_month": 41.0, "lat_issue_response_median": 3.0, "lat_pr_resolution_median": 1.0, "bus_factor": 62.0, "kpi_release_count_month": null, "kpi_release_count_month_log": null, "kpi_code_change_lines_month": 547903.0, "kpi_code_change_lines_month_log": null, "kpi_activity": 452.22, "kpi_openrank": 186.17, "kpi_attention": 145.0}, {"month": "2022-11", "kpi_commits_month": null, "kpi_commits_month_log": null, "kpi_new_issues_month": 73.0, "kpi_new_issues_month_log": null, "kpi_new_prs_month": 250.0, "kpi_new_prs_month_log": null, "kpi_active_contributors_month": 214.0, "kpi_stars_delta_month": 42.0, "lat_issue_response_median": 1.0, "lat_pr_resolution_median": 1.0, "bus_factor": 60.0, "kpi_release_count_month": null, "kpi_release_count_month_log": null, "kpi_code_change_lines_month": 789869.0, "kpi_code_change_lines_month_log": null, "kpi_activity": 526.94, "kpi_openrank": 209.56, "kpi_attention": 136.0}, {"month": "2022-12", "kpi_commits_month": null, "kpi_commits_month_log": null, "kpi_new_issues_month": 59.0, "kpi_new_issues_month_log": null, "kpi_new_prs_month": 130.0, "kpi_new_prs_month_log": null, "kpi_active_contributors_month": 159.0, "kpi_stars_delta_month": 37.0, "lat_issue_response_median": 1.0, "lat_pr_resolution_median": 3.0, "bus_factor": 54.0, "kpi_release_count_month": null, "kpi_release_count_month_log": null, "kpi_code_change_lines_month": 300779.0, "kpi_code_change_lines_month_log": null, "kpi_activity": 403.59, "kpi_openrank": 202.04, "kpi_attention": 107.0}, {"month": "2023-01", "kpi_commits_month": null, "kpi_commits_month_log": null, "kpi_new_issues_month": 74.0, "kpi_new_issues_month_log": null, "kpi_new_prs_month": 188.0, "kpi_new_prs_month_log": null, "kpi_active_contributors_month": 216.0, "kpi_stars_delta_month": 31.0, "lat_issue_response_median": 1.0, "lat_pr_resolution_median": 1.0, "bus_factor": 66.0, "kpi_release_count_month": null, "kpi_release_count_month_log": null, "kpi_code_change_lines_month": 970452.0, "kpi_code_change_lines_month_log": null, "kpi_activity": 509.61, "kpi_openrank": 205.82, "kpi_attention": 107.0}, {"month": "2023-02", "kpi_commits_month": null, "kpi_commits_month_log": null, "kpi_new_issues_month": 47.0, "kpi_new_issues_month_log": null, "kpi_new_prs_month": 203.0, "kpi_new_prs_month_log": null, "kpi_active_contributors_month": 191.0, "kpi_stars_delta_month": 47.0, "lat_issue_response_median": 1.0, "lat_pr_resolution_median": 1.0, "bus_factor": 63.0, "kpi_release_count_month": null, "kpi_release_count_month_log": null, "kpi_code_change_lines_month": 1172053.0, "kpi_code_change_lines_month_log": null, "kpi_activity": 481.54, "kpi_openrank": 192.79, "kpi_attention": 137.0}, {"month": "2023-03", "kpi_commits_month": null, "kpi_commits_month_log": null, "kpi_new_issues_month": 70.0, "kpi_new_issues_month_log": null, "kpi_new_prs_month": 222.0, "kpi_new_prs_month_log": null, "kpi_active_contributors_month": 182.0, "kpi_stars_delta_month": 40.0, "lat_issue_response_median": 1.0, "lat_pr_resolution_median": 0.0, "bus_factor": 57.0, "kpi_release_count_month": null, "kpi_release_count_month_log": null, "kpi_code_change_lines_month": 1628860.0, "kpi_code_change_lines_month_log": null, "kpi_activity": 463.18, "kpi_openrank": 182.96, "kpi_attention": 160.0}]